kcwebs
kcwebs/common
kcwebs/config
kcwebs/pid
kcwebs/tempfile
kcwebs/tempfile/kcwebs
kcwebs/tempfile/kcwebs/app
kcwebs/tempfile/kcwebs/app/api
kcwebs/tempfile/kcwebs/app/api/common
kcwebs/tempfile/kcwebs/app/api/controller
kcwebs/tempfile/kcwebs/app/api/controller/index
kcwebs/tempfile/kcwebs/app/api/controller/index/common
kcwebs/tempfile/kcwebs/app/api/controller/index/common/html
kcwebs/tempfile/kcwebs/app/api/controller/index/common/html/include
kcwebs/tempfile/kcwebs/app/api/controller/index/tpl
kcwebs/tempfile/kcwebs/app/api/controller/index/tpl/index
kcwebs/tempfile/kcwebs/app/common
kcwebs/tempfile/kcwebs/app/common/html
kcwebs/tempfile/kcwebs/app/common/html/include
kcwebs/tempfile/kcwebs/app/config
kcwebs/utill
kcwebs/utill/db
kcwebs/utill/db/sqlitedata
